hs_udata/__init__.py
hs_udata/apis/__init__.py
hs_udata/apis/base/__init__.py
hs_udata/apis/base/api.py
hs_udata/apis/stock/__init__.py
hs_udata/apis/stock/api.py
hs_udata/apis/trade/__init__.py
hs_udata/tests/__init__.py
hs_udata/tests/test.py
hs_udata/utils/__init__.py
hs_udata/utils/client.py
hs_udata/utils/common.py
hs_udata/utils/config.py
hs_udata/utils/config.yml
hs_udata/utils/connection.py
hs_udata/utils/connection_pool.py
hs_udata/utils/consts.py
hs_udata/utils/convert.py
hs_udata/utils/datetime_func.py
hs_udata/utils/decorators.py
hs_udata/utils/error.py
hs_udata-0.3.8.dist-info/METADATA
hs_udata-0.3.8.dist-info/WHEEL
hs_udata-0.3.8.dist-info/top_level.txt
hs_udata-0.3.8.dist-info/RECORD
